<?xml version="1.0" encoding="utf-8"?>
<odoo>

    <record id="view_trueformat_check_wizard_form" model="ir.ui.view">
        <field name="name">trueformat.check.wizard.form</field>
        <field name="model">trueformat.check.wizard</field>
        <field name="arch" type="xml">
            <form string="TrueFormat CSV Integrity Check">
                <sheet>
                    <group invisible="state != 'draft'">
                        <field name="csv_file" filename="csv_filename"/>
                        <field name="csv_filename" invisible="1"/>
                    </group>
                    <div invisible="state != 'draft'" class="text-muted">
                        The file is checked in-memory. Nothing is stored.
                        Limits: .csv files up to 20 MB / 250,000 rows.
                    </div>
                    <div invisible="state != 'draft'" class="alert alert-info mt-2" role="alert">
                        Requires a TrueFormat API key in
                        Settings → Technical → Parameters → System Parameters
                        (<code>trueformat.api_key</code>).
                    </div>

                    <div invisible="state != 'done'">
                        <field name="issues_found" invisible="1"/>
                        <field name="row_count" invisible="1"/>
                        <field name="result_summary" invisible="1"/>
                        <field name="preview_data" widget="trueformat_preview" nolabel="1"/>

                        <group invisible="not fixed_file" class="mt-3">
                            <field name="fixed_file" filename="fixed_filename" readonly="1"/>
                            <field name="fixed_filename" invisible="1"/>
                        </group>
                        <div invisible="not fixed_file" class="text-muted">
                            Download the corrected file above. Fix All Columns
                            repairs the whole CSV (every row): scientific
                            notation, Excel date serials, date-coerced SKUs
                            (SEP-26 → TF-serial), quotes/semicolons, and
                            leading zeros where recoverable.
                        </div>
                    </div>
                </sheet>

                <footer>
                    <button name="action_check" string="Check File" type="object"
                            class="btn-primary" invisible="state != 'draft'"/>
                    <button name="action_fix" string="Fix All Columns" type="object"
                            class="btn-primary"
                            invisible="state != 'done' or fixed_file or issues_found == 0"/>
                    <button name="action_reset" string="Check Another" type="object"
                            class="btn-secondary" invisible="state != 'done'"/>
                    <button string="Close" class="btn-secondary" special="cancel"/>
                </footer>
            </form>
        </field>
    </record>

    <record id="action_trueformat_check_wizard" model="ir.actions.act_window">
        <field name="name">CSV Integrity Check</field>
        <field name="res_model">trueformat.check.wizard</field>
        <field name="view_mode">form</field>
        <field name="target">new</field>
    </record>

</odoo>
